more_executors/__init__.py
more_executors/__init__.pyi
more_executors/asyncio.py
more_executors/asyncio.pyi
more_executors/cancel_on_shutdown.py
more_executors/cancel_on_shutdown.pyi
more_executors/flat_map.py
more_executors/flat_map.pyi
more_executors/futures.py
more_executors/futures.pyi
more_executors/map.py
more_executors/map.pyi
more_executors/poll.py
more_executors/poll.pyi
more_executors/py.typed
more_executors/retry.py
more_executors/retry.pyi
more_executors/sync.py
more_executors/sync.pyi
more_executors/throttle.py
more_executors/throttle.pyi
more_executors/timeout.py
more_executors/timeout.pyi
more_executors/_impl/__init__.py
more_executors/_impl/__init__.pyi
more_executors/_impl/asyncio.py
more_executors/_impl/asyncio.pyi
more_executors/_impl/bind.py
more_executors/_impl/bind.pyi
more_executors/_impl/cancel_on_shutdown.py
more_executors/_impl/cancel_on_shutdown.pyi
more_executors/_impl/common.py
more_executors/_impl/event.py
more_executors/_impl/executors.py
more_executors/_impl/executors.pyi
more_executors/_impl/flat_map.py
more_executors/_impl/flat_map.pyi
more_executors/_impl/helpers.py
more_executors/_impl/logwrap.py
more_executors/_impl/map.py
more_executors/_impl/map.pyi
more_executors/_impl/poll.py
more_executors/_impl/poll.pyi
more_executors/_impl/retry.py
more_executors/_impl/retry.pyi
more_executors/_impl/shared_types.pyi
more_executors/_impl/sync.py
more_executors/_impl/sync.pyi
more_executors/_impl/throttle.py
more_executors/_impl/throttle.pyi
more_executors/_impl/timeout.py
more_executors/_impl/timeout.pyi
more_executors/_impl/wrap.py
more_executors/_impl/wrapped.py
more_executors/_impl/futures/__init__.py
more_executors/_impl/futures/__init__.pyi
more_executors/_impl/futures/apply.py
more_executors/_impl/futures/apply.pyi
more_executors/_impl/futures/base.py
more_executors/_impl/futures/base.pyi
more_executors/_impl/futures/bool.py
more_executors/_impl/futures/bool.pyi
more_executors/_impl/futures/check.py
more_executors-2.11.4.dist-info/LICENSE
more_executors-2.11.4.dist-info/METADATA
more_executors-2.11.4.dist-info/WHEEL
more_executors-2.11.4.dist-info/top_level.txt
more_executors-2.11.4.dist-info/RECORD
