Metadata-Version: 2.1
Name: more-executors
Version: 2.11.4
Summary: A library of composable Python executors and futures
Home-page: https://github.com/rohanpm/more-executors
Author: Rohan McGovern
Author-email: rohan@mcgovern.id.au
License: GNU General Public License
Project-URL: Changelog, https://github.com/rohanpm/more-executors/blob/master/CHANGELOG.md
Project-URL: Documentation, https://rohanpm.github.io/more-executors/
Platform: UNKNOWN
Classifier: Development Status :: 5 - Production/Stable
Classifier: Intended Audience :: Developers
Classifier: License :: OSI Approved :: GNU General Public License v3 or later (GPLv3+)
Classifier: Programming Language :: Python :: 2
Classifier: Programming Language :: Python :: 2.6
Classifier: Programming Language :: Python :: 2.7
Classifier: Programming Language :: Python :: 3
Classifier: Topic :: Software Development :: Libraries :: Python Modules
Requires-Dist: six
Requires-Dist: futures ; python_version < "3"
Requires-Dist: monotonic ; python_version < "3.3"
Provides-Extra: prometheus
Requires-Dist: prometheus-client ; extra == 'prometheus'
